[
  {
    "username": "toothfairy",
    "team": "Holy Priests",
    "steam": "https://steamcommunity.com/profiles/76561198872641163",
    "tier": 1,
    "cost": 6,
    "teamRating": 2.47363
  },
  {
    "username": "s1me",
    "team": "Holy Priests",
    "steam": "https://steamcommunity.com/id/camelblackcompact/",
    "tier": 2,
    "cost": 4,
    "teamRating": 2.145
  },
  {
    "username": "Decoy",
    "team": "Holy Priests",
    "steam": "https://steamcommunity.com/profiles/76561199404403438",
    "tier": 3,
    "cost": 2,
    "teamRating": 1.31877
  },
  {
    "username": "Kirbitch",
    "team": "Cotton Pickers",
    "steam": "https://steamcommunity.com/profiles/76561198257075656",
    "tier": 1,
    "cost": 6,
    "teamRating": 3.02531
  },
  {
    "username": "K1rgo777",
    "team": "Cotton Pickers",
    "steam": "https://steamcommunity.com/profiles/76561199003294165",
    "tier": 2,
    "cost": 4,
    "teamRating": 2.4937
  },
  {
    "username": "family",
    "team": "Cotton Pickers",
    "steam": "https://steamcommunity.com/profiles/76561199416292715",
    "tier": 3,
    "cost": 2,
    "teamRating": 1.92834
  },
  {
    "username": "Wide",
    "team": "9/11",
    "steam": "https://steamcommunity.com/profiles/76561198392474738",
    "tier": 1,
    "cost": 6,
    "teamRating": 2.71121
  },
  {
    "username": "MV",
    "team": "9/11",
    "steam": "https://steamcommunity.com/profiles/76561198368168183",
    "tier": 2,
    "cost": 4,
    "teamRating": 2.42153
  },
  {
    "username": "CUBONS",
    "team": "9/11",
    "steam": "https://steamcommunity.com/id/cubons",
    "tier": 3,
    "cost": 2,
    "teamRating": 2.06813
  },
  {
    "username": "namejs",
    "team": "Turanskis",
    "steam": "https://steamcommunity.com/id/namejslt/",
    "tier": 1,
    "cost": 6,
    "teamRating": 2.69768
  },
  {
    "username": "L53",
    "team": "Turanskis",
    "steam": "https://steamcommunity.com/profiles/76561198366639353",
    "tier": 2,
    "cost": 4,
    "teamRating": 2.12995
  },
  {
    "username": "Sahtoms",
    "team": "Turanskis",
    "steam": "https://steamcommunity.com/id/METRODARZS",
    "tier": 3,
    "cost": 2,
    "teamRating": 2.39334
  },
  {
    "username": "romaniсh",
    "team": "Māceķļi",
    "steam": "https://steamcommunity.com/profiles/76561199439286816",
    "tier": 1,
    "cost": 6,
    "teamRating": 2.59864
  },
  {
    "username": "Rubber-",
    "team": "Māceķļi",
    "steam": "https://steamcommunity.com/id/leonskut",
    "tier": 2,
    "cost": 4,
    "teamRating": 1.94901
  },
  {
    "username": "sinAy",
    "team": "Māceķļi",
    "steam": "https://steamcommunity.com/profiles/76561198256725891",
    "tier": 3,
    "cost": 2,
    "teamRating": 1.63127
  }
]